dua/__init__.py
dua/collection.py
dua/interface.py
dua/server.py
dua-0.1.2.dist-info/licenses/LICENSE
dua-0.1.2.dist-info/METADATA
dua-0.1.2.dist-info/WHEEL
dua-0.1.2.dist-info/top_level.txt
dua-0.1.2.dist-info/RECORD
