Metadata-Version: 2.4
Name: dua
Version: 0.1.2
Summary: JSON database allowing for local or remote connection
Author-email: Oskar <mail@oskar.nz>
License: MIT License
Project-URL: Homepage, https://github.com/oskxzr/dua
Project-URL: Bug Tracker, https://github.com/oskxzr/dua/issues
Classifier: Programming Language :: Python :: 3
Classifier: License :: OSI Approved :: MIT License
Requires-Python: >=3.12
License-File: LICENSE
Requires-Dist: Flask<4.0,>=3.1
Requires-Dist: requests<3.0,>=2.32
Dynamic: license-file
